script_codes/__init__.py
script_codes/admin.py
script_codes/apps.py
script_codes/models.py
script_codes/migrations/0001_initial.py
script_codes/migrations/0002_script_codes_data.py
script_codes/migrations/0003_change_meta_options_on_script.py
script_codes/migrations/__init__.py
django_script_codes-0.3.0.dist-info/AUTHORS.rst
django_script_codes-0.3.0.dist-info/LICENSE
django_script_codes-0.3.0.dist-info/METADATA
django_script_codes-0.3.0.dist-info/WHEEL
django_script_codes-0.3.0.dist-info/top_level.txt
django_script_codes-0.3.0.dist-info/RECORD
