Metadata-Version: 2.1
Name: django-script-codes
Version: 0.3.0
Summary: Django application that provides access to the script codes standard ISO 15924.
Home-page: https://github.com/kingsdigitallab/django-script-codes
Author: Miguel Vieira
Author-email: jmvieira@gmail.com
License: MIT
Keywords: django-script-codes
Platform: UNKNOWN
Classifier: Development Status :: 3 - Alpha
Classifier: Framework :: Django :: 2.0
Classifier: Intended Audience :: Developers
Classifier: License :: OSI Approved :: MIT License
Classifier: Natural Language :: English
Classifier: Programming Language :: Python :: 3
Classifier: Programming Language :: Python :: 3.4
Classifier: Programming Language :: Python :: 3.5
Classifier: Programming Language :: Python :: 3.6
Requires-Dist: django-model-utils (>=2.0)
Requires-Dist: pycountry
